cortex_serving_client/__init__.py
cortex_serving_client/command_line_wrapper.py
cortex_serving_client/cortex_client.py
cortex_serving_client/deployment_failed.py
cortex_serving_client/hash_utils.py
cortex_serving_client/printable_chars.py
cortex_serving_client/retry_utils.py
cortex_serving_client/s3.py
cortex_serving_client/shell_utils.py
cortex_serving_client/zip_utils.py
cortex_serving_client/resources/__init__.py
cortex_serving_client/resources/main.py
cortex_serving_client-0.42.1.dist-info/LICENCE
cortex_serving_client-0.42.1.dist-info/METADATA
cortex_serving_client-0.42.1.dist-info/WHEEL
cortex_serving_client-0.42.1.dist-info/top_level.txt
cortex_serving_client-0.42.1.dist-info/RECORD
