Metadata-Version: 2.1
Name: cortex-serving-client
Version: 0.42.1
Summary: Cortex.dev ML Serving Client for Python with garbage API collection.
Home-page: https://github.com/glami/cortex-serving-client
Author: Vaclav Kosar, Antonin Hoskovec, Radek Bartyzal
Author-email: vaclav.kosar@glami.cz, antonin.hoskovec@glami.cz, radek.bartyzal@glami.cz
License: UNKNOWN
Platform: UNKNOWN
Classifier: Programming Language :: Python :: 3
Classifier: License :: OSI Approved :: MIT License
Classifier: Operating System :: OS Independent
Classifier: Topic :: Utilities
Requires-Python: >=3.6
Requires-Dist: cortex (==0.42.1)
Requires-Dist: PyYAML (>=3.12)
Requires-Dist: psycopg2-binary (>=2.8.6)
Requires-Dist: boto3 (>=1.12.11)
Requires-Dist: psutil (>=5.6.7)
